README.md
setup.py
ehsm/__init__.py
ehsm/constants.py
ehsm/ehsm.py
ehsm.egg-info/PKG-INFO
ehsm.egg-info/SOURCES.txt
ehsm.egg-info/dependency_links.txt
ehsm.egg-info/not-zip-safe
ehsm.egg-info/requires.txt
ehsm.egg-info/top_level.txt
test/test_integration.py