Metadata-Version: 2.1
Name: ehsm
Version: 1.0.0
Summary: Python bindings for the ellipticSecure PKCS11 shared library
Home-page: https://github.com/ellipticSecure/python-libehsm
Author: Kobus Grobler
Author-email: kobus.grobler@gmail.com
License: MIT
Platform: UNKNOWN
Classifier: Intended Audience :: Developers
Classifier: License :: OSI Approved :: MIT License
Classifier: Operating System :: OS Independent
Classifier: Programming Language :: Python
Classifier: Programming Language :: Python :: 2.6
Classifier: Programming Language :: Python :: 2.7
Classifier: Programming Language :: Python :: 3
